nearest_colours/__init__.py
nearest_colours/w3c.csv
nearest_colours/x11.csv
nearest_colour-1.0.0.dist-info/LICENSE.txt
nearest_colour-1.0.0.dist-info/WHEEL
nearest_colour-1.0.0.dist-info/METADATA
nearest_colour-1.0.0.dist-info/RECORD
