Metadata-Version: 2.1
Name: nearest-colour
Version: 1.0.0
Summary: Find the nearest W3C/X11 named colors to a given color
Home-page: https://github.com/pedroasad/python-nearest-colour
License: MIT
Author: Pedro Asad
Author-email: psa.exe@gmail.com
Requires-Python: >=3.8,<4.0
Classifier: License :: OSI Approved :: MIT License
Classifier: Programming Language :: Python :: 3
Classifier: Programming Language :: Python :: 3.10
Classifier: Programming Language :: Python :: 3.8
Classifier: Programming Language :: Python :: 3.9
Requires-Dist: colour (>=0.1.5,<0.2.0)
Requires-Dist: numpy (>=1.22.0,<2.0.0)
Requires-Dist: pandas (>=1.3.5,<2.0.0)
Project-URL: Repository, https://github.com/pedroasad/python-nearest-colour
